octavia_proxy/__init__.py
octavia_proxy/i18n.py
octavia_proxy/opts.py
octavia_proxy/version.py
octavia_proxy/api/__init__.py
octavia_proxy/api/app.py
octavia_proxy/api/config.py
octavia_proxy/api/root_controller.py
octavia_proxy/api/common/__init__.py
octavia_proxy/api/common/hooks.py
octavia_proxy/api/common/invocation.py
octavia_proxy/api/common/pagination.py
octavia_proxy/api/common/types.py
octavia_proxy/api/drivers/driver_factory.py
octavia_proxy/api/drivers/utils.py
octavia_proxy/api/drivers/elbv2/__init__.py
octavia_proxy/api/drivers/elbv2/driver.py
octavia_proxy/api/drivers/elbv3/__init__.py
octavia_proxy/api/drivers/elbv3/driver.py
octavia_proxy/api/v2/__init__.py
octavia_proxy/api/v2/controllers/__init__.py
octavia_proxy/api/v2/controllers/availability_zones.py
octavia_proxy/api/v2/controllers/base.py
octavia_proxy/api/v2/controllers/flavors.py
octavia_proxy/api/v2/controllers/health_monitor.py
octavia_proxy/api/v2/controllers/l7policy.py
octavia_proxy/api/v2/controllers/l7rule.py
octavia_proxy/api/v2/controllers/listener.py
octavia_proxy/api/v2/controllers/load_balancer.py
octavia_proxy/api/v2/controllers/member.py
octavia_proxy/api/v2/controllers/pool.py
octavia_proxy/api/v2/controllers/provider.py
octavia_proxy/api/v2/controllers/quotas.py
octavia_proxy/api/v2/types/__init__.py
octavia_proxy/api/v2/types/availability_zone_profile.py
octavia_proxy/api/v2/types/availability_zones.py
octavia_proxy/api/v2/types/flavors.py
octavia_proxy/api/v2/types/health_monitor.py
octavia_proxy/api/v2/types/l7policy.py
octavia_proxy/api/v2/types/l7rule.py
octavia_proxy/api/v2/types/listener.py
octavia_proxy/api/v2/types/load_balancer.py
octavia_proxy/api/v2/types/member.py
octavia_proxy/api/v2/types/pool.py
octavia_proxy/api/v2/types/provider.py
octavia_proxy/api/v2/types/quotas.py
octavia_proxy/cmd/__init__.py
octavia_proxy/cmd/api.py
octavia_proxy/common/config.py
octavia_proxy/common/constants.py
octavia_proxy/common/context.py
octavia_proxy/common/exceptions.py
octavia_proxy-1.1.1.dist-info/AUTHORS
octavia_proxy-1.1.1.dist-info/METADATA
octavia_proxy-1.1.1.dist-info/WHEEL
octavia_proxy-1.1.1.dist-info/entry_points.txt
octavia_proxy-1.1.1.dist-info/pbr.json
octavia_proxy-1.1.1.dist-info/top_level.txt
octavia_proxy-1.1.1.dist-info/RECORD
