Metadata-Version: 2.1
Name: octavia-proxy
Version: 1.1.1
Summary: Open Telekom Cloud Octavia API proxy
Home-page: UNKNOWN
Author: Open Telekom Cloud
License: UNKNOWN
Keywords: OpenStack, openstackclient, openstacksdk, Open Telekom Cloud, otc, T-Systems, Telekom
Platform: UNKNOWN
Classifier: Environment :: OpenStack
Classifier: Intended Audience :: Information Technology
Classifier: Intended Audience :: System Administrators
Classifier: License :: OSI Approved :: Apache Software License
Classifier: Operating System :: POSIX :: Linux
Classifier: Programming Language :: Python
Classifier: Programming Language :: Python :: 3.6
Classifier: Programming Language :: Python :: 3.7
Classifier: Programming Language :: Python :: 3.8
Classifier: Programming Language :: Python :: 3.9
Requires-Dist: pbr (!=2.1.0,>=2.0.0)
Requires-Dist: WSME (>=0.8.0)
Requires-Dist: pecan (>=1.3.2)
Requires-Dist: WebOb (>=1.8.2)
Requires-Dist: requests (>=2.14.2)
Requires-Dist: keystonemiddleware (>=4.17.0)
Requires-Dist: oslo.config (>=5.2.0)
Requires-Dist: oslo.log (>=4.3.0)
Requires-Dist: oslo.middleware (>=4.0.1)
Requires-Dist: oslo.policy (>=2.1.0)
Requires-Dist: oslo.reports (>=1.18.0)
Requires-Dist: octavia-lib (>=2.4.0)
Requires-Dist: python-dateutil
Requires-Dist: otcextensions
Requires-Dist: validatetoken
